ftsm/__init__.py
ftsm/ftsm.py
ftsm-0.1.0.dist-info/LICENSE
ftsm-0.1.0.dist-info/METADATA
ftsm-0.1.0.dist-info/WHEEL
ftsm-0.1.0.dist-info/top_level.txt
ftsm-0.1.0.dist-info/RECORD
