Metadata-Version: 2.1
Name: ftsm
Version: 0.1.0
Summary: A Finite Transactional State Machine.
Home-page: https://github.com/ketan86/ftsm
Author: Ketan Patel
Author-email: ketan86ecer@gmail.com
License: MIT License
Keywords: ftsm package
Platform: UNKNOWN
Classifier: License :: OSI Approved :: MIT License
Classifier: Programming Language :: Python :: 3.6
Classifier: Programming Language :: Python :: 3.7
